[
  {
    "full_name": "open-sauced/open-sauced",
    "stargazers_count": 497,
    "open_issues_count": 25,
    "forks_count": 144
  },
  {
    "full_name": "jdesboeufs/connect-mongo",
    "stargazers_count": 1829,
    "open_issues_count": 6,
    "forks_count": 340
  },
  {
    "full_name": "jamiebuilds/the-super-tiny-compiler",
    "stargazers_count": 21004,
    "open_issues_count": 17,
    "forks_count": 2254
  },
  {
    "full_name": "cpojer/js-codemod",
    "stargazers_count": 1098,
    "open_issues_count": 3,
    "forks_count": 122
  },
  {
    "full_name": "expressjs/express",
    "stargazers_count": 54674,
    "open_issues_count": 177,
    "forks_count": 9243
  },
  {
    "full_name": "expressjs/expressjs.com",
    "stargazers_count": 4131,
    "open_issues_count": 53,
    "forks_count": 1129
  },
  {
    "full_name": "facebook/jest",
    "stargazers_count": 36800,
    "open_issues_count": 1611,
    "forks_count": 5384
  },
  {
    "full_name": "freeCodeCamp/devdocs",
    "stargazers_count": 26753,
    "open_issues_count": 124,
    "forks_count": 1793
  },
  {
    "full_name": "piotrwitek/react-redux-typescript-guide",
    "stargazers_count": 11486,
    "open_issues_count": 36,
    "forks_count": 853
  },
  {
    "full_name": "microsoft/vscode",
    "stargazers_count": 122598,
    "open_issues_count": 5636,
    "forks_count": 20400
  },
  {
    "full_name": "okonet/lint-staged",
    "stargazers_count": 9235,
    "open_issues_count": 111,
    "forks_count": 344
  },
  {
    "full_name": "k88hudson/git-flight-rules",
    "stargazers_count": 37292,
    "open_issues_count": 14,
    "forks_count": 2800
  },
  {
    "full_name": "sahat/hackathon-starter",
    "stargazers_count": 32384,
    "open_issues_count": 43,
    "forks_count": 7422
  },
  {
    "full_name": "remix-run/react-router",
    "stargazers_count": 44227,
    "open_issues_count": 46,
    "forks_count": 8568
  },
  {
    "full_name": "microsoft/TypeScript-React-Starter",
    "stargazers_count": 10808,
    "open_issues_count": 203,
    "forks_count": 1145
  },
  {
    "full_name": "DefinitelyTyped/DefinitelyTyped",
    "stargazers_count": 36209,
    "open_issues_count": 763,
    "forks_count": 25889
  },
  {
    "full_name": "KaterinaLupacheva/my-projects-dashboard",
    "stargazers_count": 48,
    "open_issues_count": 0,
    "forks_count": 9
  },
  {
    "full_name": "malgamves/CommunityWriterPrograms",
    "stargazers_count": 1318,
    "open_issues_count": 11,
    "forks_count": 204
  },
  {
    "full_name": "awesome-selfhosted/awesome-selfhosted",
    "stargazers_count": 65818,
    "open_issues_count": 120,
    "forks_count": 4877
  },
  {
    "full_name": "microsoft/TypeScript",
    "stargazers_count": 74951,
    "open_issues_count": 5276,
    "forks_count": 9835
  },
  {
    "full_name": "up-for-grabs/up-for-grabs.net",
    "stargazers_count": 2386,
    "open_issues_count": 43,
    "forks_count": 1168
  },
  {
    "full_name": "tailwindlabs/tailwindcss-intellisense",
    "stargazers_count": 1431,
    "open_issues_count": 39,
    "forks_count": 88
  },
  {
    "full_name": "tailwindlabs/tailwindcss",
    "stargazers_count": 48018,
    "open_issues_count": 54,
    "forks_count": 2247
  },
  {
    "full_name": "yangshun/tech-interview-handbook",
    "stargazers_count": 60136,
    "open_issues_count": 6,
    "forks_count": 8353
  },
  {
    "full_name": "postcss/postcss",
    "stargazers_count": 25261,
    "open_issues_count": 13,
    "forks_count": 1408
  },
  {
    "full_name": "mrdoob/three.js",
    "stargazers_count": 74949,
    "open_issues_count": 459,
    "forks_count": 29307
  },
  {
    "full_name": "testjavascript/nodejs-integration-tests-best-practices",
    "stargazers_count": 1376,
    "open_issues_count": 40,
    "forks_count": 67
  },
  {
    "full_name": "swisskyrepo/PayloadsAllTheThings",
    "stargazers_count": 30843,
    "open_issues_count": 15,
    "forks_count": 8502
  },
  {
    "full_name": "prisma/prisma-examples",
    "stargazers_count": 2847,
    "open_issues_count": 69,
    "forks_count": 706
  },
  {
    "full_name": "tediko/planets-fact",
    "stargazers_count": 40,
    "open_issues_count": 0,
    "forks_count": 12
  }
]